PyEvalJS/__init__.py
PyEvalJS/error.py
PyEvalJS/runtime.py
PyEvalJS/utils.py
PyEvalJS/libs/linux/libChakraCore.so
PyEvalJS/libs/osx/libChakraCore.dylib
PyEvalJS/libs/windows/x64/ChakraCore.dll
PyEvalJS/libs/windows/x86/ChakraCore.dll
PyEvalJS-1.0.0.dist-info/LICENSE
PyEvalJS-1.0.0.dist-info/METADATA
PyEvalJS-1.0.0.dist-info/WHEEL
PyEvalJS-1.0.0.dist-info/top_level.txt
PyEvalJS-1.0.0.dist-info/RECORD
