Metadata-Version: 2.1
Name: PyEvalJS
Version: 1.0.0
Summary: Run JavaScript Code in Python through the Microsoft Chakra engine
Home-page: https://github.com/Satireven/PyEvalJS
Author: Satireven
Author-email: satireven@gmail.com
License: MIT
Keywords: Python JavaScript js-engine Chakra ChakraCore V8
Platform: UNKNOWN
Classifier: Development Status :: 5 - Production/Stable
Classifier: Intended Audience :: Developers
Classifier: Natural Language :: English
Classifier: License :: OSI Approved :: MIT License
Classifier: Programming Language :: Python
Classifier: Programming Language :: Python :: 2
Classifier: Programming Language :: Python :: 2.7
Classifier: Programming Language :: Python :: 3
Classifier: Programming Language :: Python :: 3.3
Classifier: Programming Language :: Python :: 3.4
Classifier: Programming Language :: Python :: 3.5
Classifier: Programming Language :: Python :: 3.6
Classifier: Programming Language :: Python :: 3.7
Requires-Python: >2.6, !=3.0.*, !=3.1.*, !=3.2.*
